{
    "durations": {
        "Anamanaguchi - Miku ft. Hatsune Miku (Lyric Video).mp3": 238.584,
        "BUTCHER VANITY ft. Yi Xi.mp3": 185.64,
        "Catchy !\uff1f \u29f8 r-906 feat. Ci flower.mp3": 180.048,
        "Chinozo '\u30b0\u30c3\u30d0\u30a4\u5ba3\u8a00' feat.FloweR.mp3": 176.568,
        "DECO\uff0a27 - \u30b4\u30fc\u30b9\u30c8\u30eb\u30fc\u30eb feat. \u521d\u97f3\u30df\u30af.mp3": 206.4,
        "DECO\uff0a27 - \u30d2\u30d0\u30ca feat. \u521d\u97f3\u30df\u30af.mp3": 202.92,
        "DECO\uff0a27 - \u30e2\u30cb\u30bf\u30ea\u30f3\u30b0 feat. \u521d\u97f3\u30df\u30af.mp3": 181.368,
        "DECO\uff0a27 - \u30e9\u30d3\u30c3\u30c8\u30db\u30fc\u30eb feat. \u521d\u97f3\u30df\u30af.mp3": 162.096,
        "DECO\uff0a27 - \u30f4\u30a1\u30f3\u30d1\u30a4\u30a2 feat. \u521d\u97f3\u30df\u30af.mp3": 180.048,
        "Giga - '\u52a3\u7b49\u4e0a\u7b49'(BRING IT ON) ft.\u93e1\u97f3\u30ea\u30f3\u30fb\u30ec\u30f3\u3010MV\u3011.mp3": 235.128,
        "Hatsune Miku - Ievan Polkka.mp3": 149.4,
        "KIRA - MONSTER ft. GUMI English (Original Song).mp3": 217.728,
        "Kikuo - \u3054\u3081\u3093\u306d \u3054\u3081\u3093\u306d.mp3": 287.112,
        "Kikuo - \u611b\u3057\u3066\u611b\u3057\u3066\u611b\u3057\u3066.mp3": 250.128,
        "Machine Love (feat. Kasane Teto).mp3": 286.488,
        "Neru - \u30ed\u30b9\u30c8\u30ef\u30f3\u306e\u53f7\u54ed(Lost One's Weeping) feat. Kagamine Rin.mp3": 217.872,
        "Neru - \u8131\u6cd5\u30ed\u30c3\u30af(Law-evading Rock) feat. Kagamine Len.mp3": 187.032,
        "Orangestar - DAYBREAK FRONTLINE (feat. IA) Official Video.mp3": 217.68,
        "Orangestar - \u30a2\u30b9\u30ce\u30e8\u30be\u30e9\u54e8\u6212\u73ed (feat. IA) Official Video.mp3": 176.568,
        "Porter Robinson - Goodbye To A World (Audio).mp3": 330.12,
        "Why Do I (with Hatsune Miku).mp3": 155.376,
        "Yukopi - \u5f37\u98a8\u30aa\u30fc\u30eb\u30d0\u30c3\u30af (feat.\u6b4c\u611b\u30e6\u30ad).mp3": 136.488,
        "[1080P Full\u98a8] Luka Luka\u2605Night Fever \u30eb\u30ab\u30eb\u30ab\u2605\u30ca\u30a4\u30c8\u30d5\u30a3\u30fc\u30d0\u30fc \u5de1\u97f3\u30eb\u30ab Project DIVA English lyrics romaji subtitles.mp3": 241.344,
        "[1080P Full\u98a8] World is Mine \u30ef\u30fc\u30eb\u30c9\u30a4\u30ba\u30de\u30a4\u30f3 -Hatsune Miku \u521d\u97f3\u30df\u30af Project DIVA English lyrics Romaji PDFT.mp3": 255.84,
        "[30fps Full\u98a8] Romeo and Cinderella \u30ed\u30df\u30aa\u3068\u30b7\u30f3\u30c7\u30ec\u30e9 -Hatsune Miku \u521d\u97f3\u30df\u30af DIVA English lyrics romaji subtitles.mp3": 280.368,
        "[60fps Full] PoPiPo \u307d\u3063\u3074\u3063\u307d\u30fc - Hatsune Miku \u521d\u97f3\u30df\u30af DIVA Dreamy theater \u30c9\u30ea\u30fc\u30df\u30fc\u30b7\u30a2\u30bf\u30fc English Romaji.mp3": 179.808,
        "wowaka \u300e\u30a2\u30f3\u30ce\u30a6\u30f3\u30fb\u30de\u30b6\u30fc\u30b0\u30fc\u30b9\u300ffeat. \u521d\u97f3\u30df\u30af \u29f8 wowaka - Unknown Mother-Goose (Official Video) ft. Hatsune Miku.mp3": 285.72,
        "wowaka \u300e\u30ed\u30fc\u30ea\u30f3\u30ac\u30fc\u30eb\u300ffeat. \u521d\u97f3\u30df\u30af \u29f8 wowaka - Rollin Girl (Official Video) ft. Hatsune Miku.mp3": 196.104,
        "\u2517\uff5c\u2235\uff5c\u2513\u544a\u767d\u30e9\u30a4\u30d0\u30eb\u5ba3\u8a00\uff0fHoneyWorks feat.GUMI.mp3": 233.112,
        "\u300c\uff2d\uff36\u300d\u3000\u5343\u672c\u685c\u3000WhiteFlame feat \u521d\u97f3\u30df\u30af.mp3": 244.104,
        "\u3010GUMI\u3011KING\u3010Kanaria\u3011.mp3": 134.904,
        "\u3010GUMI\u3011\u30a8\u30f3\u30f4\u30a3\u30fc\u30d9\u30a4\u30d3\u30fc\u3010Kanaria\u3011.mp3": 135.912,
        "\u3010GUMI\u3011\u900f\u660e\u30a8\u30ec\u30b8\u30fc\u3010\u30aa\u30ea\u30b8\u30ca\u30eb\u66f2\u3011.mp3": 224.136,
        "\u3010GUMI\u3011\u9154\u3044\u3069\u308c\u77e5\u3089\u305a\u3010Kanaria\u3011.mp3": 135.0,
        "\u3010Gumi English\u3011Candle Queen\u3010Original Song Collaboration\u3011.mp3": 153.192,
        "\u3010HD\u3011 \u516d\u5146\u5e74\u3068\u4e00\u591c\u7269\u8a9e \u3010IA\u30aa\u30ea\u30b8\u30ca\u30eb\u66f2\u30fbPV\u4ed8\u3011- KEMU VOXX.mp3": 220.2,
        "\u3010IA\u3011\u5c11\u5e74\u30d6\u30ec\u30a4\u30f4.mp3": 287.52,
        "\u3010Kagamine Rin\u30fbLen\u3011Electric Angel \uff02\u3048\u308c\u304f\u3068\u308a\u3063\u304f\u30fb\u3048\u3093\u3058\u3047\u3045\uff02\u3010VOCALOID-PV\u3011.mp3": 191.688,
        "\u3010Official Music Video\u3011\u30e2\u30df\u30a2\u30b2\u30f2\u30b7\u30e3\u30ab\u30a2\u30b2\u30f2\uffe4Momiagewo Shakaagewo.mp3": 207.744,
        "\u3010VOCALOID Original\u3011ECHO\u3010Gumi English\u3011.mp3": 244.968,
        "\u3010Vocaloid Original\u3011Copycat\u3010GUMI English\u3011.mp3": 284.616,
        "\u3010\u516c\u5f0f\u3011 \u30c0\u30fc\u30ea\u30f3\u30c0\u30f3\u30b9\uff0f\u304b\u3044\u308a\u304d\u30d9\u30a2 feat.\u521d\u97f3\u30df\u30af.mp3": 207.216,
        "\u3010\u516c\u5f0f\u3011 \u30d9\u30ce\u30e0\uff0f\u304b\u3044\u308a\u304d\u30d9\u30a2 feat.flower.mp3": 203.112,
        "\u3010\u521d\u97f3\u30df\u30af(40\u334d)\u3011 \u304b\u3089\u304f\u308a\u30d4\u30a8\u30ed Karakuri Pierrot\u3010\u30aa\u30ea\u30b8\u30ca\u30eb\u3011.mp3": 294.792,
        "\u3010\u521d\u97f3\u30df\u30af\u3011 \u30a6\u30df\u30e6\u30ea\u6d77\u5e95\u8b5a \u3010\u30aa\u30ea\u30b8\u30ca\u30eb\u66f2\u3011.mp3": 238.752,
        "\u3010\u521d\u97f3\u30df\u30af\u3011 \u604b\u611b\u88c1\u5224 Love Trial \u3010\u30aa\u30ea\u30b8\u30ca\u30ebMV\u3011.mp3": 221.784,
        "\u3010\u521d\u97f3\u30df\u30af\u3011\u3000\u3042\u3044\u3057\u3066\u3044\u305f\u306e\u306b\u3000\u3010\u30aa\u30ea\u30b8\u30ca\u30eb\u3011.mp3": 219.168,
        "\u3010\u521d\u97f3\u30df\u30af\u3011\u30d3\u30bf\u30fc\u30c1\u30e7\u30b3\u30c7\u30b3\u30ec\u30fc\u30b7\u30e7\u30f3\u3010syudou\u3011.mp3": 197.952,
        "\u3010\u53ef\u4e0d\u3011\u30ad\u30e5\u30fc\u30c8\u306a\u30ab\u30ce\u30b8\u30e7\u3010syudou\u3011.mp3": 131.136,
        "\u3010\u6d1b\u5929\u4f9d\u539f\u521b\u3011\u6211\u7684\u60b2\u4f24\u662f\u6c34\u505a\u7684 \u3010Luo Tianyi Original\u3011Bad Bad Water.mp3": 226.032,
        "\u304a\u3061\u3083\u3081\u6a5f\u80fd\u3000\u30cb\u30b3\u30ab\u30e9\u3000onvocal.mp3": 246.888,
        "\u304d\u3085\u3046\u304f\u3089\u308a\u3093 \u29f8 \u3044\u3088\u308f feat.\u53ef\u4e0d\uff08Kyu-kurarin \u29f8 Iyowa feat.Kafu\uff09.mp3": 216.12,
        "\u3055\u3088\u306a\u3089\u30d7\u30ea\u30f3\u30bb\u30b9 \u29f8 \u521d\u97f3\u30df\u30af.mp3": 126.048,
        "\u3058\u3093 \u29f8 \u30a2\u30e4\u30ce\u306e\u5e78\u798f\u7406\u8ad6 (IA)\u3010OFFICIAL MUSIC VIDEO\u3011.mp3": 333.792,
        "\u3058\u3093 \u29f8 \u30ab\u30b2\u30ed\u30a6\u30c7\u30a4\u30ba\u3010OFFICIAL MUSIC VIDEO\u3011.mp3": 252.192,
        "\u3058\u3093 \u29f8 \u30b5\u30de\u30fc\u30bf\u30a4\u30e0\u30ec\u30b3\u30fc\u30c9 (IA)\u3010OFFICIAL MUSIC VIDEO\u3011.mp3": 270.168,
        "\u3058\u3093 \u29f8 \u30ed\u30b9\u30bf\u30a4\u30e0\u30e1\u30e2\u30ea\u30fc (IA)\u3010OFFICIAL MUSIC VIDEO\u3011.mp3": 283.42857142857144,
        "\u3060\u308c\u304b\u306e\u5fc3\u81d3\u306b\u306a\u308c\u305f\u306a\u3089 \u29f8\u30e6\u30ea\u30a4\u30fb\u30ab\u30ce\u30f3 feat.GUMI.mp3": 230.208,
        "\u306c\u3086\u308a - \u30d5\u30e9\u30b8\u30fc\u30eb \u29f8 GUMI \uff1a Fragile.mp3": 269.376,
        "\u306c\u3086\u308a - \u30ed\u30a6\u30ef\u30fc \u29f8 Flower \uff1a Lower one's eyes.mp3": 230.04,
        "\u307f\u304d\u3068P \u300e \u30ed\u30ad \u300f MV.mp3": 230.448,
        "\u307f\u304d\u3068P \u300e \u5c11\u5973\u30ec\u30a4 \u300f MV.mp3": 289.68,
        "\u308f\u305f\u3057\u306e\u30a2\u30fc\u30eb - \u548c\u7530\u305f\u3051\u3042\u304d(\u304f\u3089\u3052P) \u29f8 R - KurageP.mp3": 214.056,
        "\u30a4\u30ac\u30af - \u91cd\u97f3\u30c6\u30c8.mp3": 120.384,
        "\u30a8\u30b4\u30a4\u30b9\u30c8\u29f8flower.mp3": 220.032,
        "\u30a8\u30b4\u30ed\u30c3\u30af(long ver.) \u29f8 \u3059\u308a\u3043 feat.\u93e1\u97f3\u30ec\u30f3.mp3": 170.496,
        "\u30aa\u30fc\u30d0\u30fc\u30e9\u30a4\u30c9 - \u91cd\u97f3\u30c6\u30c8SV[\u5409\u7530\u591c\u4e16].mp3": 138.528,
        "\u30ad\u30e3\u30c3\u30c8\u30e9\u30d3\u30f3\u30b0 \u29f8 \u9999\u690e\u30e2\u30a4\u30df feat. \u53ef\u4e0d.mp3": 116.376,
        "\u30ad\u30e3\u30f3\u30c7\u30a3\u30fc\u30af\u30c3\u30ad\u30fc\u30c1\u30e7\u30b3\u30ec\u30fc\u30c8\u3000\ud83c\udf6d\ud83c\udf6a\ud83c\udf6b\u521d\u97f3\u30df\u30af\u30fb\u91cd\u97f3\u30c6\u30c8SV.mp3": 168.6,
        "\u30b7\u30e3\u30eb\u30eb\uff0fflower.mp3": 228.672,
        "\u30c1\u30e5\u30eb\u30ea\u30e9\u30fb\u30c1\u30e5\u30eb\u30ea\u30e9\u30fb\u30c0\u30c3\u30c0\u30c3\u30c0\uff01 -  \u548c\u7530\u305f\u3051\u3042\u304d(\u304f\u3089\u3052P) \u29f8 Chururira Chururira Daddadda! - KurageP.mp3": 196.368,
        "\u30c6\u30c8\u30ea\u30b9 \u29f8 \u91cd\u97f3\u30c6\u30c8SV.mp3": 142.608,
        "\u30c6\u30ec\u30ad\u30e3\u30b9\u30bf\u30fc\u30d3\u30fc\u30dc\u30fc\u30a4(long ver.) \u29f8 \u3059\u308a\u3043 feat.\u93e1\u97f3\u30ec\u30f3.mp3": 164.544,
        "\u30cf\u30c1  MV\u300c\u30de\u30c8\u30ea\u30e7\u30b7\u30ab\u300dHACHI \u29f8 MATORYOSHKA.mp3": 200.064,
        "\u30cf\u30c1 - \u30c9\u30fc\u30ca\u30c4\u30db\u30fc\u30eb , HACHI - DONUT HOLE.mp3": 210.216,
        "\u30cf\u30c1 - \u7802\u306e\u60d1\u661f feat.\u521d\u97f3\u30df\u30af , HACHI - DUNE ft.Miku Hatsune.mp3": 239.088,
        "\u30d4\u30ce\u30ad\u30aa\u30d4\u30fc - \u306d\u3047\u306d\u3047\u306d\u3047\u3002 feat. \u93e1\u97f3\u30ea\u30f3\u30fb\u521d\u97f3\u30df\u30af \u29f8 Nee Nee Nee..mp3": 210.672,
        "\u30d4\u30ce\u30ad\u30aa\u30d4\u30fc - \u533f\u540dM feat. \u521d\u97f3\u30df\u30af\u30fbARuFa \u29f8 Anonymous M.mp3": 159.912,
        "\u30d4\u30ce\u30ad\u30aa\u30d4\u30fc - \u795e\u3063\u307d\u3044\u306a feat. \u521d\u97f3\u30df\u30af \u29f8 God-ish.mp3": 204.048,
        "\u30d4\u30ce\u30ad\u30aa\u30d4\u30fc - \u8ee2\u751f\u6797\u6a8e feat. \u521d\u97f3\u30df\u30af \u29f8 Reincarnation Apple.mp3": 218.664,
        "\u30d4\u30ce\u30ad\u30aa\u30d4\u30fc - \u9b54\u6cd5\u5c11\u5973\u3068\u30c1\u30e7\u30b3\u30ec\u3090\u30c8 feat. \u521d\u97f3\u30df\u30af \u29f8 Magical Girl and Chocolate.mp3": 187.656,
        "\u30d5\u30a9\u30cb\u30a4 \u29f8 phony - kafu [\u30aa\u30ea\u30b8\u30ca\u30eb].mp3": 188.232,
        "\u30e1\u30ba\u30de\u30e9\u30a4\u30b6\u30fc \u29f8 \u521d\u97f3\u30df\u30af\u30fb\u91cd\u97f3\u30c6\u30c8SV.mp3": 157.008,
        "\u30f4\u30a3\u30e9\u30f3 \u29f8 flower\u30fb\u3066\u306b\u3092\u306f (villain\u29f8 flower\u30fbteniwoha).mp3": 200.208,
        "\u4eba\u30de\u30cb\u30a2 - \u91cd\u97f3\u30c6\u30c8.mp3": 127.248,
        "\u516b\u738b\u5b50P \u00d7 Giga\u300cGimme\u00d7Gimme feat. \u521d\u97f3\u30df\u30af\u30fb\u93e1\u97f3\u30ea\u30f3\u300d.mp3": 220.944,
        "\u516b\u738b\u5b50P \u300c\u6c17\u307e\u3050\u308c\u30e1\u30eb\u30b7\u30a3  feat. \u521d\u97f3\u30df\u30af\u300d(6\u29f815\u767a\u58f2Best AL\u300cEight\u300d\u53ce\u9332\uff09.mp3": 208.368,
        "\u521d\u97f3\u30df\u30af\u306e\u6d88\u5931(THE END OF HATSUNE MIKU) - cosMo\uff20\u66b4\u8d70P.mp3": 290.136,
        "\u5929\u30ce\u5f31\uff0f164 feat.GUMI\uff08\u516c\u5f0f).mp3": 192.936,
        "\u6625\u5d50 \u29f8 \u521d\u97f3\u30df\u30af.mp3": 154.08,
        "\u67ca\u30de\u30b0\u30cd\u30bf\u30a4\u30c8 - \u30de\u30fc\u30b7\u30e3\u30eb\u30fb\u30de\u30ad\u30b7\u30de\u30a4\u30b6\u30fc \u29f8 \u53ef\u4e0d.mp3": 165.048,
        "\u690e\u540d\u3082\u305f(siinamota) - Young Girl A \u29f8 \u5c11\u5973A.mp3": 242.112,
        "\u6df7\u6c8c\u30d6\u30ae \u29f8 jon-YAKITORY, \u521d\u97f3\u30df\u30af -Konton Boogie \u29f8 jon-YAKITORY, Hatsune Miku-.mp3": 154.68,
        "\u795e\u306e\u307e\u306b\u307e\u306b - \u308c\u308b\u308a\u308afeat.\u30df\u30af&\u30ea\u30f3&GUMI \u29f8 At God's Mercy - rerulili feat.Vocaloids.mp3": 254.712,
        "\u7a32\u8449\u66c7\u300e\u30e9\u30b0\u30c8\u30ec\u30a4\u30f3\u300fVo. \u6b4c\u611b\u30e6\u30ad.mp3": 251.88,
        "\u7a32\u8449\u66c7\u300e\u30ed\u30b9\u30c8\u30a2\u30f3\u30d6\u30ec\u30e9\u300fVo. \u6b4c\u611b\u30e6\u30ad.mp3": 202.656,
        "\u7a32\u8449\u66c7\u300e\u79c1\u306f\u96e8\u300fVo. \u6b4c\u611b\u30e6\u30ad.mp3": 220.464,
        "\u8056\u69cd\u7206\u88c2\u30dc\u30fc\u30a4 - \u308c\u308b\u308a\u308afeat.\u93e1\u97f3\u30ec\u30f3 \u29f8 Holy Lance Explosion Boy - rerulili feat.KagamineLen.mp3": 209.448,
        "\u8133\u6f3f\u70b8\u88c2\u30ac\u30fc\u30eb - \u308c\u308b\u308a\u308afeat.\u521d\u97f3\u30df\u30af&GUMI \u29f8 Brain Fluid Explosion Girl - rerulili feat.miku&gumi.mp3": 191.616,
        "\u963f\u543d\u306e\u30d3\u30fc\u30c4 \u29f8 flower.mp3": 205.392
    },
    "hasImages": false
}